{"objectID":668903,"isHighlight":false,"accessionNumber":"31.3.175c","accessionYear":"1931","isPublicDomain":true,"primaryImage":"https://images.metmuseum.org/CRDImages/eg/original/DP338041.jpg","primaryImageSmall":"https://images.metmuseum.org/CRDImages/eg/web-large/DP338041.jpg","additionalImages":[],"constituents":null,"department":"Egyptian Art","objectName":"Relief, tomb of Meketre","title":"Relief fragment from the tomb of Meketre","culture":"","period":"Middle Kingdom","dynasty":"Dynasty 12","reign":"reign of Amenemhat I, early","portfolio":"","artistRole":"","artistPrefix":"","artistDisplayName":"","artistDisplayBio":"","artistSuffix":"","artistAlphaSort":"","artistNationality":"","artistBeginDate":"","artistEndDate":"","artistGender":"","artistWikidata_URL":"","artistULAN_URL":"","objectDate":"ca. 1981–1975 B.C.","objectBeginDate":-1981,"objectEndDate":-1975,"medium":"Limestone, paint","dimensions":"H. 3.9 cm (1 9/16 in.); W. 8.2 cm (3 1/4 in.); D. 3.1 cm (1 1/4 in.)","measurements":[{"elementName":"Overall","elementDescription":"c","elementMeasurements":{"Depth":3.1,"Height":3.9,"Width":8.2}}],"creditLine":"Rogers Fund, 1931","geographyType":"From","city":"","state":"","county":"","country":"Egypt","region":"Upper Egypt, Thebes","subregion":"Southern Asasif","locale":"Tomb of Meketre (TT 280, MMA 1101)","locus":"","excavation":"MMA excavations, 1920","river":"","classification":"","rightsAndReproduction":"","linkResource":"","metadataDate":"2020-03-02T21:50:01.377Z","repository":"Metropolitan Museum of Art, New York, NY","objectURL":"https://www.metmuseum.org/art/collection/search/668903","tags":null,"objectWikidata_URL":"","isTimelineWork":false,"GalleryNumber":""}