{"Present location": "EGYPTIAN MUSEUM [01/001] CAIRO EM", "Inventory number": "JE 34191", "Dating": "5TH DYNASTY", "Archaeological Site": "ABU SIR/BUSIRIS", "Category": "RELIEF", "Material": "LIMESTONE", "Technique": "STONE-TECHNIQUE; HIGH RELIEF", "Height": "55 cm", "Name": "Low-Relief of the Heb Sed", "Description": "Three limestone reliefs that depict some episodes from a festival called Heb Sed are preserved in the Egyptian Museum. This festival was celebrated to reaffirm the reign of the king and show that he was still vital and capable of ruling for another period. The king is represented in the form of the god Osiris, wrapped in his short ceremonial mantle and wearing the Atef Crown. He comes out of his palace and performs the ceremonial run that would prove his vitality, an essential part of this festivity."}