{"Present location": "NATIONAL MUSEUM OF IRELAND [30/002] DUBLIN", "Inventory number": "1904:486", "Dating": "ROMAN PERIOD", "Archaeological Site": "IHNASIYA EL-MADINA/HERAKLEOPOLIS", "Category": "ANIMAL/HYBRID FIGURINE", "Material": "BRONZE", "Technique": "CASTING", "Height": "3 cm", "Width": "1.3 cm", "Name": "Animal figurine", "Description": "Bronze, partly corroded figure of a quadruped, identified by the excavators as perhaps a young goat. The style is Roman rather than Pharaonic, reflecting the general change in material culture at this period."}