{"Present location": "LIVERPOOL MUSEUM [03/061] LIVERPOOL", "Inventory number": "1973.4.112", "Dating": "PTOLEMAIC PERIOD", "Archaeological Site": "UNKNOWN", "Category": "RELIEF", "Material": "LIMESTONE", "Technique": "HEWN; LOW RELIEF", "Height": "17 cm", "Width": "21 cm", "Name": "Relief fragment", "Description": "A fragment of relief in fine limestone, depicting a Ptolemaic king facing to the left. The small straight beard, high contours of relief and the uraeus coil are indicative of a date after Ptolemy II. There are traces of red paint on the face. This is probably a sculptor's trial piece."}