{"Present location": "MUSEO ARQUEOL\u00c3\u201cGICO NACIONAL [21/007] MADRID", "Inventory number": "16128", "Dating": "CHALCOLITHIC PERIOD (not before); PREDYNASTIC PERIOD; EARLY DYNASTIC PERIOD/THINITE PERIOD (not after)", "Archaeological Site": "UNKNOWN", "Category": "JUG", "Material": "CLAY; POTTERY", "Technique": "FORMED BY HAND", "Height": "11.1 cm", "Diameter": "9,4 cm", "Name": "Vase", "Description": "Ovoidal vase, with outward turning rim and unstable base which ends in a point. The paste and very rough surface are reddish in colour."}