{"Present location": "KMKG - MRAH [07/003] BRUSSELS", "Inventory number": "E.5566", "Dating": "LATE PERIOD", "Archaeological Site": "UNKNOWN", "Category": "SHABTI", "Material": "POTTERY", "Technique": "FORMED BY HAND; PAINTED; ENGRAVED; FAYENCE; ENGRAVED", "Height": "10.2 cm", "Name": "Shabti", "Description": "This small shabti of green faience carries as its only inscription the name and title of the owner and his wife. Unfortunately the hieroglyphic signs indicating the names are badly deteriorated.  The statuette comes from the collection of G. Hagemans."}