{"_id":"mip-o1059524","_source":{"multimedia":["Repository/Documents/2014_10/8_21/1a4c0513_5961_4eb5_98e4_a3be0165f75a/max_00472448_001.jpg","Repository/Documents/2014_10/1_6/61361eee_8795_4023_a030_a3b70065db31/max_00030503_001.jpg","Repository/Documents/2014_10/10_14/0f6d9ddd_5f4f_4c8d_a875_a3c000eb11bc/max_00564180_001.jpg"],"name":[{"reference":{"@link":{"type":"reference"},"admin":{"uid":"mip-x6305","id":"x6305","uuid":"80809a6b-e76a-31ea-9e1e-0dc0c09b53fd"}},"value_combined":"_currency-bar|currency-bar","hierarchy":[[{"@link":{"type":"reference"},"summary_title":"currency","summary_title_combined":"_currency|currency","admin":{"uid":"mip-x6304","checksum":2153605177,"id":"x6304","uuid":"0d984a76-68e9-3603-b21e-7e7e75961f22"}},{"@link":{"type":"reference"},"summary_title":"currency-bar","summary_title_combined":"_currency-bar|currency-bar","admin":{"uid":"mip-x6305","id":"x6305","uuid":"80809a6b-e76a-31ea-9e1e-0dc0c09b53fd"}}]],"sort":"currency-bar","type":"object name","value":"currency-bar"}],"xtemplate":{"brief":"{\"Object Type\":{\"value\":\"<span class=\\\"vterm\\\">currency-bar</span>\",\"id\":\"x6305\"},\"Museum number\":\"1894,1207.2\",\"Cultures/periods\":{\"id\":\"x14451\",\"value\":\"<span class=\\\"vterm\\\">Roman Imperial</span>\"},\"Production date\":\"4thC (late)\",\"Production place\":[{\"id\":\"x38508\",\"value\":\"<span class=\\\"vprefix\\\">Attributed at:</span> <span class=\\\"vterm\\\">Sirmium</span>\"}],\"Findspot\":[{\"id\":\"x45593\",\"value\":\"<span class=\\\"vprefix\\\">Excavated/Findspot:</span> <span class=\\\"vterm\\\">Braşov (city)</span>\"}]}"}},"sort":["currency-bar",2.042785]}