{"artifact_name": "lute", "Object Type": ["lute"], "Museum number": ["Af.3404"], "Description": [" Lute made of wood, with four tuning pegs (\"keys\") with wire strings, inlaid with pearl shell. "], "Production date": ["1865 (before)"], "Production place": [" Made in: Egypt "], "Findspot": [" Found/Acquired: Egypt "], "Materials": [" wood ", " mother-of-pearl "], "Dimensions": [" Height: 58.20 centimetres ", " Width: 10.20 centimetres ", " Depth: 8.50 centimetres "], "Curator's comments": ["Probably acquired by Henry Christy on his visit to the Eastern Mediterranean in 1850."], "Location": ["Not on display"], "Acquisition name": ["Bequeathed by: Henry Christy"], "Acquisition date": ["1865"], "Department": ["Africa, Oceania and the Americas"], "Registration number": ["Af.3404"], "Additional IDs": [" CDMS number: Af186?C1.3404 (old CDMS no.) "]}