{"_id":"mip-o416030","_source":{"multimedia":["Repository/Documents/2014_11/7_13/841e9a13_c25c_4238_9e0b_a3dc00d63c9d/max_01292929_001.jpg","Repository/Documents/2014_11/7_13/eb5521b0_8960_4e6a_89b2_a3dc00d63e68/max_01292930_001.jpg","Repository/Documents/2014_11/7_13/cdacff22_60bb_460f_ad8e_a3dc00d63fe8/max_01292931_001.jpg","Repository/Documents/2014_11/7_13/45823857_d3c5_4aa2_ad96_a3dc00d64399/max_01292933_001.jpg"],"name":[{"reference":{"@link":{"type":"reference"},"admin":{"uid":"mip-x9845","id":"x9845","uuid":"6a877ddc-a945-3780-8030-11bc984cb8ce"}},"note":[{"type":"comment","value":"?"}],"value_combined":"_vase|vase","hierarchy":[[{"@link":{"type":"reference"},"summary_title":"container","summary_title_combined":"_container|container","admin":{"uid":"mip-x6133","checksum":3364628183,"id":"x6133","uuid":"ddfb3db1-d386-3916-878d-1475ec188bf9"}},{"@link":{"type":"reference"},"summary_title":"vessel","summary_title_combined":"_vessel|vessel","admin":{"uid":"mip-x9862","checksum":3106672417,"id":"x9862","uuid":"2ae9f441-3fb5-3234-b153-8687ee49ef8c"}},{"@link":{"type":"reference"},"summary_title":"vase","summary_title_combined":"_vase|vase","admin":{"uid":"mip-x9845","id":"x9845","uuid":"6a877ddc-a945-3780-8030-11bc984cb8ce"}}]],"sort":"vase","type":"object name","value":"vase"},{"reference":{"@link":{"type":"reference"},"admin":{"uid":"mip-x5597","id":"x5597","uuid":"baafeb60-73a4-3b04-a78a-4f67cb04a99b"}},"note":[{"type":"comment","value":"?"}],"value_combined":"_bowl|bowl","hierarchy":[[{"@link":{"type":"reference"},"summary_title":"container","summary_title_combined":"_container|container","admin":{"uid":"mip-x6133","checksum":3364628183,"id":"x6133","uuid":"ddfb3db1-d386-3916-878d-1475ec188bf9"}},{"@link":{"type":"reference"},"summary_title":"vessel","summary_title_combined":"_vessel|vessel","admin":{"uid":"mip-x9862","checksum":2479386490,"id":"x9862","uuid":"2ae9f441-3fb5-3234-b153-8687ee49ef8c"}},{"@link":{"type":"reference"},"summary_title":"bowl","summary_title_combined":"_bowl|bowl","admin":{"uid":"mip-x5597","id":"x5597","uuid":"baafeb60-73a4-3b04-a78a-4f67cb04a99b"}}]],"type":"object name","value":"bowl"}],"xtemplate":{"brief":"{\"Object Type\":[{\"value\":\"<span class=\\\"vterm\\\">vase</span>\",\"id\":\"x9845\"},{\"value\":\"<span class=\\\"vterm\\\">bowl</span>\",\"id\":\"x5597\"}],\"Museum number\":\"1888,0601.41\",\"Cultures/periods\":[{\"id\":\"x14428\",\"value\":\"<span class=\\\"vterm\\\">Ptolemaic</span>\"},{\"id\":\"x14452\",\"value\":\"<span class=\\\"vterm\\\">Roman Period</span>\"}],\"Production date\":\"1stC BC - 2ndC AD\",\"Production place\":[{\"id\":\"x30300\",\"value\":\"<span class=\\\"vprefix\\\">Made in:</span> <span class=\\\"vterm\\\">Lower Egypt</span>\"}],\"Findspot\":[{\"id\":\"x113864\",\"value\":\"<span class=\\\"vprefix\\\">Excavated/Findspot:</span> <span class=\\\"vterm\\\">Naukratis</span>\"}]}"}},"sort":["vase",3.7784972]}