{"artifact_name": "bead", "Object Type": ["bead"], "Museum number": ["1894,1101.103"], "Description": [" Barrel-shaped agate bead; perforated through the long axis for suspension; polished surface. "], "Cultures/periods": [" Cypro-Archaic (?) ", " Cypro-Classical (?) ", " Eastern Mediterranean "], "Production date": ["750BC-300BC"], "Production place": [" Made in: Cyprus (?) ", " Made in: Levant (?) ", " Made in: Egypt (?) "], "Excavator/field collector": ["Excavated by: Turner Bequest Excavations, Amathus"], "Findspot": [" Excavated/Findspot: Amathus, Site D, tomb 37 "], "Materials": ["agate"], "Technique": [" perforated ", " polished "], "Dimensions": [" Length: 4 centimetres "], "Bibliographic references": ["Murray, Smith and Walters 1900 / Excavations in Cyprus (p.117, Tomb 37)"], "Location": ["Not on display"], "Acquisition name": ["From: Turner Bequest Excavations, Amathus"], "Funder name": ["Funded by: Emma Tourner Turner (bequest)"], "Acquisition date": ["1894"], "Department": ["Greek and Roman"], "Registration number": ["1894,1101.103"]}