{"_id":"mip-o1571028","_source":{"multimedia":["Repository/Documents/2014_10/12_14/ebcd0833_d1b3_4145_8acc_a3c200f57ae1/max_00725549_001.jpg","Repository/Documents/2014_10/12_14/19a2a9b1_e652_4c83_9af5_a3c200f58156/max_00725551_001.jpg","Repository/Documents/2014_10/12_16/49252fa4_18fd_4fc2_8b1f_a3c2010ea7b3/max_00736727_001.jpg","Repository/Documents/2014_10/12_16/3bc41075_4559_45d1_b40e_a3c2010eb593/max_00736731_001.jpg"],"name":[{"reference":{"@link":{"type":"reference"},"admin":{"uid":"mip-x310309","id":"x310309","uuid":"984011dd-dddd-3026-aa32-7651d7c825d1"}},"value_combined":"_heavy_chalice|heavy chalice","hierarchy":[[{"@link":{"type":"reference"},"summary_title":"<unauthorised>","summary_title_combined":"_<unauthorised>|<unauthorised>","admin":{"uid":"mip-x25539","checksum":186804981,"id":"x25539","uuid":"7ca8ff70-9e50-33e5-9536-5e120d37aedf"}},{"@link":{"type":"reference"},"summary_title":"heavy chalice","summary_title_combined":"_heavy_chalice|heavy chalice","admin":{"uid":"mip-x310309","id":"x310309","uuid":"984011dd-dddd-3026-aa32-7651d7c825d1"}}]],"sort":"heavy chalice","type":"object name","value":"heavy chalice"}],"xtemplate":{"brief":"{\"Object Type\":{\"value\":\"<span class=\\\"vterm\\\">heavy chalice</span>\",\"id\":\"x310309\"},\"Museum number\":\"1888,0601.460.b\",\"Cultures/periods\":[{\"id\":\"x13817\",\"value\":\"<span class=\\\"vterm\\\">East Greek</span>\"},{\"id\":\"x13613\",\"value\":\"<span class=\\\"vterm\\\">Archaic Greek</span>\"}],\"Production date\":\"580BC-570BC\",\"Production place\":[{\"id\":\"x28201\",\"value\":\"<span class=\\\"vprefix\\\">Made in:</span> <span class=\\\"vterm\\\">Chios</span>\"}],\"Findspot\":[{\"id\":\"x113864\",\"value\":\"<span class=\\\"vprefix\\\">Excavated/Findspot:</span> <span class=\\\"vterm\\\">Naukratis</span>\"}]}"}},"sort":["heavy chalice",3.4030123]}