{"artifact_name": "transport amphora", "Object Type": ["transport amphora"], "Museum number": ["1925,0119.386"], "Description": [" Handle sliver of a probably Rhodian pottery transport amphora at neck join. Clay medium light buff-brown. Rectangular stamp. "], "Cultures/periods": ["Hellenistic"], "Production date": ["300BC-250BC"], "Production place": [" Made in: Rhodes (?) "], "Findspot": [" Found/Acquired: Naukratis "], "Materials": ["pottery"], "Dimensions": [" Height: 5.80 centimetres (Max preserved) ", " Height: 0.80 centimetres (Stamp) ", " Width: 4 centimetres (Handle min.) ", " Width: 1 centimetres (Stamp) "], "$Inscriptions": [" "], "Curator's comments": ["Petrie Diary (EES Archive XVII 47) p. 206, 20."], "Bibliographic references": ["Villing et al 2013-2015 / Naukratis: Greeks in Egypt (JB.1709)"], "Location": ["Not on display"], "Acquisition name": ["Donated by: Egypt Exploration Fund"], "Acquisition date": ["1886"], "Department": ["Greek and Roman"], "Registration number": ["1925,0119.386"], "Conservation": ["Treatment: 24 Jul 2000"]}