{"artifact_name": "print", "Object Type": ["print"], "Museum number": ["W,6.10"], "Description": [" Rest on the flight into Egypt, with on the right the seated Virgin suckling Christ Child, and on the left St Joseph leaning against a tree and sleeping; after Luca Cambiaso Engraving "], "Producer name": [" After: Luca Cambiaso ", " Published by: Giovanni Orlandi "], "School/style": ["Italian"], "Production date": ["1590-1640"], "Production place": [" Published in: Rome (city) "], "Materials": ["paper"], "Technique": ["engraving"], "Dimensions": [" Height: 226 millimetres (trimmed) ", " Width: 272 millimetres "], "$Inscriptions": [" "], "Location": ["Not on display"], "Subjects": ["rest on flight into egypt"], "Associated names": ["Representation of: Holy Family"], "Acquisition name": ["Bequeathed by: Sir Hans Sloane (probably)"], "Acquisition date": ["1753"], "Acquisition notes": ["with Philipe's oval stamp and the initials washed out, but so badly cut as to exclude a Cracherode provenance"], "Department": ["Prints and Drawings"], "Registration number": ["W,6.10"]}