{"artifact_name": "scarab", "Object Type": ["scarab"], "Museum number": ["E48113"], "Description": [" White or green glazed steatite scarab: engraved on the base with a crude design of quadruped (dog?) with crosshatched body moving right, above its back the plant of Lower Egypt. In front of the animal an indeterminate sigm, perhaps 'nfr'. Top abraded. "], "Cultures/periods": [" New Kingdom (late) ", " 26th Dynasty "], "Excavator/field collector": ["Excavated by: Charles Francis Tyrwhitt Drake (?)"], "Findspot": [" Excavated/Findspot: Syria (desert) "], "Materials": ["steatite"], "Technique": [" glazed ", " engraved "], "Dimensions": [" Length: 19 millimetres ", " Width: 15 millimetres ", " Depth: 8 millimetres "], "Bibliographic references": ["Giveon R 1985a / Egyptian scarabs from Western Asia from the collections of the British Museum (p.188, no.36)"], "Location": ["Not on display"], "Condition": ["Fair; top abraded."], "Subjects": [" animal ", " plant ", " symbol "], "Associated places": [" Emblem of: Lower Egypt "], "Acquisition name": ["Donated by: Sir Augustus Wollaston Franks"], "Acquisition date": ["1873"], "Department": ["Middle East"], "BM/Big number": ["E48113"], "Registration number": ["1873,1129.1"]}