{"artifact_name": "vessel", "Object Type": ["vessel"], "Museum number": ["1891,0701.200"], "Description": [" Sherd (base). Made of cobalt, green-black painted and green glazed (decayed), crackled pottery (buff-pink). "], "Producer name": ["Made by: Ghazzal (?)"], "Cultures/periods": ["Mamluk dynasty"], "Production date": ["15thC"], "Excavator/field collector": ["Excavated by: Egypt Exploration Fund"], "Findspot": [" Found/Acquired: Fustat "], "Materials": ["pottery"], "Technique": [" painted ", " glazed "], "Dimensions": [" Height: 6.50 centimetres ", " Width: 5.50 centimetres "], "$Inscriptions": [" "], "Bibliographic references": ["Gibbs 1994 / Mamluk Underglaze-Decorated Wares: Some Evidence from Fustat (fig.86)"], "Location": ["On display (G42/dc6)"], "Acquisition name": ["Donated by: Egypt Exploration Fund"], "Acquisition date": ["1891"], "Department": ["Middle East"], "Registration number": ["1891,0701.200"]}