{"artifact_name": "vessel", "Object Type": ["vessel"], "Description": [" Lower body fragment of East Greek pottery open vessel, krater or dinos. Two goats to left; preserved are the hindquarters and rear leg of the first, the horn of the second; outline rosettes as fill; bands of thinned glaze above and below the figured zone; added red on hindquarters and belly of the left goat. "], "School/style": ["Wild Goat Style"], "Cultures/periods": [" East Greek ", " Archaic Greek "], "Production date": ["600BC-575BC"], "Production place": [" Made in: North Ionia "], "Findspot": [" Found/Acquired: Naukratis "], "Materials": ["pottery"], "Technique": ["painted"], "Dimensions": [" Height: 7 centimetres ", " Thickness: 0.90 centimetres ", " Width: 6.50 centimetres "], "Curator's comments": ["Object owned and held by the Greco-Roman Museum, Alexandria. This record is included in the British Museum database as part of the Museum\u2019s Naukratis Project, a research collaboration that aims to virtually re-unite finds from the ancient port city of Naukratis, now distributed over 80 museums worldwide."], "Bibliographic references": [" Venit 1988 / Greek Painted Pottery from Naukratis in Egyptian Museums (p. 14, no. 42 pl. 10) ", " Villing et al 2013-2015 / Naukratis: Greeks in Egypt (GG.914) "], "Location": ["Not on display"], "Department": ["External"], "Additional IDs": [" Miscellaneous number: 9346 (Accession Number) "]}