{"artifact_name": "vessel; ostracon", "Object Type": [" vessel ", " ostracon "], "Museum number": ["EA55693"], "Description": [" Ostracon, fragment (two pieces joined) of the shoulder-section of pale-red pottery vessel, fabric is grey in section, interior very worn, exterior covered with a cream-coloured slip and with remains of two lines of black-painted hieratic text identifying the contents as year 8 wine of the Aten domain from the western river. "], "Cultures/periods": ["18th Dynasty (late)"], "Excavator/field collector": ["Excavated by: Egypt Exploration Society"], "Findspot": [" Excavated/Findspot: Amarna, el-, TA:21-22/213 Maru-Aten "], "Materials": ["pottery"], "Technique": ["slipped"], "Dimensions": [" Height: 5.50 centimetres (max) ", " Width: 8.90 centimetres (max) "], "$Inscriptions": [" "], "Curator's comments": ["Peet & Woolley, City of Akhenaten I. Pl. LXIV fig. 47"], "Bibliographic references": ["Trismegistos / An interdisciplinary portal of papyrological and epigraphic resources (393177) (http://www.trismegistos.org/text/393177)"], "Location": ["Not on display"], "Condition": ["fair (incomplete - two pieces joined)"], "Associated names": ["Named in inscription: Aten (domain of)"], "Acquisition date": ["1922"], "Department": ["Egypt and Sudan"], "BM/Big number": ["EA55693"], "Registration number": ["1922,1014.123"]}