{"artifact_name": "comb", "Object Type": ["comb"], "Museum number": ["EA21893"], "Description": [" Wooden comb with animal-shaped handle. "], "Cultures/periods": ["New Kingdom"], "Findspot": [" Found/Acquired: Medinet Habu (Thebes) "], "Materials": ["wood"], "Dimensions": [" Height: 16.30 centimetres ", " Weight: 26 grammes ", " Width: 1.10 centimetres ", " Depth: 8 centimetres "], "Curator's comments": ["."], "Location": ["Not on display"], "Exhibition history": [" 2013 July - October, Cambridge, The Fitzwilliam Museum, Origins of the Afro Comb "], "Condition": ["fair"], "Acquisition name": ["Purchased from: Rev Greville John Chester"], "Acquisition date": ["1887"], "Department": ["Egypt and Sudan"], "BM/Big number": ["EA21893"], "Registration number": ["1887,0730.22"], "Conservation": [" Treatment: 14 Feb 2014 ", " Treatment: 25 Apr 2013 "]}