{"artifact_name": "ostracon", "Object Type": ["ostracon"], "Museum number": ["EA66241"], "Description": [" Ostracon, fragment of the body of a red-brown pottery vessel, the fabric is partially grey in section, the interior is slightly grooved and covered with a dark-brown resinous deposit, the exterior is covered with a red-brown slip and remains of five lines of black-painted demotic text. "], "Cultures/periods": ["Graeco-Roman"], "Excavator/field collector": ["Excavated by: Egypt Exploration Society"], "Findspot": [" Excavated/Findspot: Osireion (Abydos) "], "Materials": ["pottery"], "Technique": ["slipped"], "Dimensions": [" Height: 6.40 centimetres (max) ", " Width: 7.80 centimetres (max) "], "$Inscriptions": [" "], "Bibliographic references": [" Wangstedt 1976-1977 / Demotische Ostraca Varia I (pp.17-18 no. 8.) ", " Trismegistos / An interdisciplinary portal of papyrological and epigraphic resources (51758) (http://www.trismegistos.org/text/51758) ", " Alm\u00e1sy-Martin 2020 / Demotic, Greek and Coptic ostraca from Abydos in the British Museum (no.10) "], "Location": ["Not on display"], "Condition": ["fair"], "Acquisition date": ["1926"], "Department": ["Egypt and Sudan"], "BM/Big number": ["EA66241"], "Registration number": ["1926,0728.262"], "Additional IDs": [" Miscellaneous number: O.BM Abydos Dem. 10 (Edition abbreviation according to Oates et al. 2001) "]}