{"artifact_name": "ostracon", "Object Type": ["ostracon"], "Museum number": ["EA55765"], "Description": [" Ostracon, fragment from the body of a brown pottery ribbed vessel, exterior covered with a brown slip and remains of five lines of Coptic text written in black ink, now faded, containing a list of \"Bundles\". "], "Cultures/periods": ["Coptic"], "Production date": ["6thC-8thC"], "Excavator/field collector": [" Excavated by: Byzantine Research Fund ", " Excavated by: Reginald Campbell Thompson "], "Findspot": [" Found/Acquired: Wadi Sarga "], "Materials": ["pottery"], "Technique": ["slipped"], "Dimensions": [" Height: 87 millimetres (max) ", " Width: 65 millimetres (max) "], "$Inscriptions": [" "], "Inscription subject": ["financial"], "Bibliographic references": [" Crum & Bell 1922 / Wadi Sarga: Coptic and Greek texts (p.125) ", " Trismegistos / An interdisciplinary portal of papyrological and epigraphic resources (87637) (http://www.trismegistos.org/text/87637) "], "Location": ["Not on display"], "Condition": ["fair (text faded)"], "Acquisition name": ["Donated by: Byzantine Research Fund"], "Acquisition date": ["1923"], "Department": ["Egypt and Sudan"], "BM/Big number": ["EA55765"], "Registration number": ["1923,0327.32"], "Additional IDs": [" Miscellaneous number: O.Sarga 148 (text edition abbreviation according to Oates et al 2001) "]}