{"_id":"mip-o367902","_source":{"multimedia":["Repository/Documents/2018_9/24_11/4d37ab01_6f62_42f6_8124_a96500be619d/max_15315c.jpg","Repository/Documents/2018_9/24_11/9bd6d381_bc09_4035_a593_a96500be632b/max_15315d.jpg","Repository/Documents/2018_9/24_11/59a5b96d_1dd7_4602_a1cc_a96500be5e81/max_15315a.jpg","Repository/Documents/2018_9/24_11/d2d4d311_332b_46a1_8b02_a96500be6026/max_15315b.jpg"],"name":[{"reference":{"@link":{"type":"reference"},"admin":{"uid":"mip-x8993","id":"x8993","uuid":"38e59a74-215e-3f55-a0bc-bab35a8bbe80"}},"value_combined":"_shabti|shabti","hierarchy":[[{"@link":{"type":"reference"},"summary_title":"sculpture","summary_title_combined":"_sculpture|sculpture","admin":{"uid":"mip-x8949","checksum":1322060481,"id":"x8949","uuid":"5da4d4c3-ae96-3503-a873-24b20458514c"}},{"@link":{"type":"reference"},"summary_title":"figure","summary_title_combined":"_figure|figure","admin":{"uid":"mip-x6729","checksum":798855759,"id":"x6729","uuid":"99eae8d8-5c2a-3df6-92a8-7618da395b9c"}},{"@link":{"type":"reference"},"summary_title":"shabti","summary_title_combined":"_shabti|shabti","admin":{"uid":"mip-x8993","id":"x8993","uuid":"38e59a74-215e-3f55-a0bc-bab35a8bbe80"}}],[{"@link":{"type":"reference"},"summary_title":"religious/ritual equipment","summary_title_combined":"_religious/ritual_equipment|religious/ritual equipment","admin":{"uid":"mip-x8736","checksum":2542146099,"id":"x8736","uuid":"58ef191a-96fa-30f2-a3f3-56b340970c32"}},{"@link":{"type":"reference"},"summary_title":"funerary equipment","summary_title_combined":"_funerary_equipment|funerary equipment","admin":{"uid":"mip-x6946","checksum":930331792,"id":"x6946","uuid":"302edeef-38a9-3a3a-b1c8-84f45c143f4b"}},{"@link":{"type":"reference"},"summary_title":"shabti","summary_title_combined":"_shabti|shabti","admin":{"uid":"mip-x8993","id":"x8993","uuid":"38e59a74-215e-3f55-a0bc-bab35a8bbe80"}}]],"sort":"shabti","type":"object name","value":"shabti"}],"xtemplate":{"brief":"{\"Object Type\":{\"value\":\"<span class=\\\"vterm\\\">shabti</span>\",\"id\":\"x8993\"},\"Museum number\":\"EA15315\",\"Findspot\":[{\"id\":\"x17904\",\"value\":\"<span class=\\\"vprefix\\\">Found/Acquired:</span> <span class=\\\"vterm\\\">Egypt</span>\"}]}"}},"sort":["shabti",4.0027165]}