{"artifact_name": "box; vegetal remains", "Object Type": [" box ", " vegetal remains "], "Museum number": ["EA8532"], "Description": [" Square sycomore fig wood box; painted decoration on plaster: two representations of Anubis on a plinth on the lid; representations of Khepri and Anubis on the sides; columns of Hieroglyphic text on all surfaces; inside are twenty dom palm fruits. "], "Findspot": [" Found/Acquired: Egypt "], "Materials": [" sycomore fig wood ", " dom palm fruit "], "Technique": [" painted ", " plastered "], "Dimensions": [" Height: 23.50 centimetres ", " Weight: 3.50 kilograms ", " Width: 24.30 centimetres ", " Depth: 24.30 centimetres "], "$Inscriptions": [" "], "Location": ["Not on display"], "Condition": ["fair"], "Subjects": ["ancient egyptian deity"], "Associated names": [" Representation of: Anubis ", " Representation of: Khepri "], "Acquisition name": ["Purchased from: Somerset Lowry-Corry, 2nd Earl of Belmore"], "Acquisition date": ["1843"], "Department": ["Egypt and Sudan"], "BM/Big number": ["EA8532"], "Registration number": ["1843,0507.381"], "Additional IDs": [" Miscellaneous number: BS.8532 (Birch Slip Number) "]}