{"artifact_name": "tomb-painting", "Object Type": ["tomb-painting"], "Museum number": ["EA43465"], "Description": [" Tomb painting made of plaster, grid pattern visible, with polychrome painted representation of man seated with hieroglyphs above. "], "Cultures/periods": ["New Kingdom"], "Findspot": [" Found/Acquired: Egypt "], "Materials": ["plaster"], "Technique": ["painted"], "Dimensions": [" Height: 26 centimetres ", " Width: 23.50 centimetres "], "$Inscriptions": [" "], "Location": ["Not on display"], "Condition": ["fair (incomplete)"], "Acquisition name": ["Purchased from: William Talbot Ready"], "Acquisition date": ["1907"], "Department": ["Egypt and Sudan"], "BM/Big number": ["EA43465"], "Registration number": ["1907,0112.76"]}