{"artifact_name": "textile; cloth", "Object Type": [" textile ", " cloth "], "Museum number": ["EA6504"], "Description": [" Small, irregular textile fragment; undyed linen cloth of medium quality; undecorated and edges ragged. The weave is plain [warp faced simple tabby] and the threads are S-spun and S-spliced; the stitch gauge is warp c.28 per 10mm and weft 16 per 10mm. "], "Production date": ["2200BC-600BC"], "Findspot": [" Found/Acquired: Egypt "], "Materials": ["linen"], "Technique": ["plain weave"], "Dimensions": [" Length: 23 centimetres ", " Width: 31.50 centimetres "], "Curator's comments": ["Information from Hero Granger-Taylor [1992]"], "Location": ["Not on display"], "Condition": ["fair"], "Department": ["Egypt and Sudan"], "BM/Big number": ["EA6504"], "Registration number": [".6504"], "Additional IDs": [" Miscellaneous number: BS.6504 (Birch Slip Number) "]}