{"artifact_name": "stela", "Object Type": ["stela"], "Museum number": ["EA240"], "Description": [" Round-topped limestone stela divided into three registers: 1 - Wedjat-eyes and jackals. 2 - Four rows of Hieroglyphic text. 3 - Standing male figure and small kneeling female figure before offerings. "], "Cultures/periods": ["12th Dynasty"], "Findspot": [" Found/Acquired: Egypt "], "Materials": ["limestone"], "Dimensions": [" Height: 52 centimetres ", " Weight: 15 kilograms ", " Width: 34 centimetres ", " Depth: 5 centimetres "], "$Inscriptions": [" "], "Bibliographic references": ["Scott-Moncrieff 1912 / Hieroglyphic texts from Egyptian stelae, etc., in the British Museum, Part 2. (pl.32)"], "Location": ["Not on display"], "Condition": ["fair"], "Subjects": ["eye of horus"], "Acquisition name": ["Purchased from: Joseph Sams"], "Acquisition date": ["1834"], "Department": ["Egypt and Sudan"], "BM/Big number": ["EA240"], "Registration number": [".240"], "Additional IDs": [" Miscellaneous number: BS.240 (Birch Slip Number) "]}