{"_id":"mip-o3706630","_source":{"multimedia":["Repository/Documents/2023_10/23_9/0fe80c90_70a2_4566_b75f_b0a400987528/YCA86092.jpg"],"name":[{"reference":{"@link":{"type":"reference"},"admin":{"uid":"mip-x5832","id":"x5832","uuid":"bfac40cc-6453-3ac7-b4ae-46147e7519d3"}},"value_combined":"_cast|cast","hierarchy":[[{"@link":{"type":"reference"},"summary_title":"production/replication","summary_title_combined":"_production/replication|production/replication","admin":{"uid":"mip-x8592","checksum":2118750132,"id":"x8592","uuid":"90b09efa-c46a-3c5a-b76f-0dc5855a359f"}},{"@link":{"type":"reference"},"summary_title":"cast","summary_title_combined":"_cast|cast","admin":{"uid":"mip-x5832","id":"x5832","uuid":"bfac40cc-6453-3ac7-b4ae-46147e7519d3"}}]],"sort":"cast","type":"object name","value":"cast"}],"xtemplate":{"brief":"{\"Object Type\":{\"value\":\"<span class=\\\"vterm\\\">cast</span>\",\"id\":\"x5832\"},\"Museum number\":\"EA91087\",\"Production date\":\"late 19th century - early 20th century\"}"}},"sort":["cast",3.8352456]}