{"artifact_name": "relief", "Object Type": ["relief"], "Museum number": ["EA61067"], "Description": [" Sandstone panel depicting a kneeling woman suckling a child in sunk relief; traces of blue, green and white colouring. "], "Cultures/periods": ["Graeco-Roman"], "Findspot": [" Found/Acquired: Egypt "], "Materials": ["sandstone"], "Dimensions": [" Length: 11.80 centimetres ", " Thickness: 3.20 centimetres ", " Width: 10 centimetres "], "Location": ["Not on display"], "Condition": ["fair - surface worn"], "Department": ["Egypt and Sudan"], "BM/Big number": ["EA61067"], "Registration number": [".61067"]}