{"artifact_name": "kohl-tube; kohl-stick", "Object Type": [" kohl-tube ", " kohl-stick "], "Museum number": ["EA6182"], "Description": [" Ivory kohl-tube with a wooden kohl-stick; no base; wooden remains inside. "], "Findspot": [" Excavated/Findspot: Saqqara (Memphis) "], "Materials": [" wood ", " ivory "], "Dimensions": [" Diameter: 2.90 centimetres ", " Height: 9.90 centimetres ", " Weight: 78 grammes "], "Location": ["Not on display"], "Condition": ["fair"], "Acquisition name": ["Purchased from: Giuseppe Zitelli"], "Acquisition date": ["1847"], "Department": ["Egypt and Sudan"], "BM/Big number": ["EA6182"], "Registration number": ["1847,1125.4"]}