{"artifact_name": "cowroid", "Object Type": ["cowroid"], "Museum number": ["EA40632"], "Description": [" Faded brown steatite cowroid, decorated. "], "Cultures/periods": ["Second Intermediate"], "Findspot": [" Found/Acquired: Egypt "], "Materials": ["steatite"], "Dimensions": [" Length: 1.90 centimetres ", " Width: 1.30 centimetres "], "Location": ["Not on display"], "Condition": ["good"], "Acquisition name": ["Purchased from: I \u00c9lias G\u00e9jou"], "Acquisition date": ["1904"], "Department": ["Egypt and Sudan"], "BM/Big number": ["EA40632"], "Registration number": ["1904,0409.2070"]}