{"_id":"mip-o320006","_source":{"multimedia":["Repository/Documents/2014_10/11_16/11588092_7e65_4fdc_9306_a3c10116f2c8/max_00676023_001.jpg","Repository/Documents/2014_10/11_16/178ba49f_48ed_454c_ba8f_a3c10116f55c/00676025_001.JPG","Repository/Documents/2014_10/11_16/4686770f_8e0f_42d2_a274_a3c10116f9b6/max_00676027_001.jpg"],"name":[{"reference":{"@link":{"type":"reference"},"admin":{"uid":"mip-x6729","id":"x6729","uuid":"99eae8d8-5c2a-3df6-92a8-7618da395b9c"}},"value_combined":"_figure|figure","hierarchy":[[{"@link":{"type":"reference"},"summary_title":"sculpture","summary_title_combined":"_sculpture|sculpture","admin":{"uid":"mip-x8949","checksum":4233206721,"id":"x8949","uuid":"5da4d4c3-ae96-3503-a873-24b20458514c"}},{"@link":{"type":"reference"},"summary_title":"figure","summary_title_combined":"_figure|figure","admin":{"uid":"mip-x6729","id":"x6729","uuid":"99eae8d8-5c2a-3df6-92a8-7618da395b9c"}}]],"sort":"figure","type":"object name","value":"figure"}],"xtemplate":{"brief":"{\"Object Type\":{\"value\":\"<span class=\\\"vterm\\\">figure</span>\",\"id\":\"x6729\"},\"Museum number\":\"EA13394\",\"Findspot\":[{\"id\":\"x30299\",\"value\":\"<span class=\\\"vprefix\\\">Excavated/Findspot:</span> <span class=\\\"vterm\\\">Thebes (historic - Upper Egypt)</span>\"}]}"}},"sort":["figure",4.6839156]}