{"artifact_name": "textile; garment; tunic; ribbon", "Object Type": [" textile ", " garment ", " tunic ", " ribbon "], "Museum number": ["EA72500"], "Description": [" Decorative ribbon in red wool ground with dark blue borders, with a brocaded design; Design in yellow and green wool and undyed linen, well-spaced large lozenges and smaller lozenges arranged in bars; Warp: S spun Z ply wool, c.12tpc; Weft: S spun wool, c.7tpc in main area, brocading in S spun Z ply green and yellow wool and undyed linen (grouped together by 3 or 4); Edges: simple selvedges or cut and fragmentary "], "Cultures/periods": [" Coptic ", " Byzantine "], "Production date": ["7thC-9thC"], "Production place": [" Made in: Egypt "], "Findspot": [" Excavated/Findspot: Egypt "], "Materials": [" wool ", " linen "], "Technique": [" plain weave ", " brocaded ", " dyed "], "Dimensions": [" Height: 30 centimetres ", " Width: 3.10 centimetres "], "Curator's comments": ["Unreg. 119; Found in drawer of unnumbered textiles in cupbaord P; Will have once been a trimming on a garment, probably a tunic; Information from Hero Granger-Taylor (7.7.1992)"], "Location": ["Not on display"], "Condition": ["Fair; Colours good"], "Department": ["Egypt and Sudan"], "BM/Big number": ["EA72500"], "Registration number": ["1990,0612.119"], "Additional IDs": [" Miscellaneous number: Unreg.119 "]}